cubed_xarray/__init__.py
cubed_xarray/cubedmanager.py
cubed_xarray/tests/__init__.py
cubed_xarray/tests/test_wrapping.py
cubed_xarray/tests/test_xarray.py
cubed_xarray-0.0.8.dist-info/LICENSE
cubed_xarray-0.0.8.dist-info/METADATA
cubed_xarray-0.0.8.dist-info/WHEEL
cubed_xarray-0.0.8.dist-info/entry_points.txt
cubed_xarray-0.0.8.dist-info/top_level.txt
cubed_xarray-0.0.8.dist-info/RECORD
