Metadata-Version: 2.2
Name: cubed-xarray
Version: 0.0.8
Summary: Interface for using cubed with xarray for parallel computation.
Author-email: Tom Nicholas <tomnicholas1@googlemail.com>
License: Apache-2
Project-URL: homepage, https://github.com/xarray-contrib/cubed-xarray
Project-URL: documentation, https://github.com/xarray-contrib/cubed-xarray#readme
Project-URL: repository, https://github.com/xarray-contrib/cubed-xarray
Classifier: Development Status :: 3 - Alpha
Classifier: Environment :: Console
Classifier: Intended Audience :: Science/Research
Classifier: License :: OSI Approved :: Apache Software License
Classifier: Operating System :: OS Independent
Classifier: Programming Language :: Python
Classifier: Programming Language :: Python :: 3.10
Classifier: Programming Language :: Python :: 3.11
Classifier: Programming Language :: Python :: 3.12
Classifier: Topic :: Scientific/Engineering
Requires-Python: >=3.10
License-File: LICENSE
Requires-Dist: numpy>=1.22
Requires-Dist: xarray>=2024.09.0
Requires-Dist: cubed>=0.23.0
Provides-Extra: test
Requires-Dist: cubed[diagnostics]; extra == "test"
Requires-Dist: dill; extra == "test"
Requires-Dist: pre-commit; extra == "test"
Requires-Dist: ruff; extra == "test"
Requires-Dist: pytest-mypy; extra == "test"
Requires-Dist: pytest-cov; extra == "test"
Requires-Dist: pytest; extra == "test"
